Metadata-Version: 2.1
Name: meowmeowlib
Version: 0.0.1
Summary: Simple file functions
Home-page: https://www.youtube.com/watch?v=dQw4w9WgXcQ
Author: Surya Teja Pallapu
Author-email: spallapu2@gitam.in
License: MIT
Platform: UNKNOWN
Classifier: Development Status :: 5 - Production/Stable
Classifier: Intended Audience :: Education
Classifier: Operating System :: Microsoft :: Windows :: Windows 10
Classifier: License :: OSI Approved :: MIT License
Classifier: Programming Language :: Python :: 3
License-File: LICENCE.txt
